code_savior/__init__.py
code_savior/ai_model.py
code_savior/config.py
code_savior/interface.py
code_savior/main.py
code_savior/utils/__init__.py
code_savior/utils/doc_utils.py
code_savior/utils/git_utils.py
code_savior/utils/utils.py
code_savior-1.0.dist-info/LICENSE
code_savior-1.0.dist-info/METADATA
code_savior-1.0.dist-info/WHEEL
code_savior-1.0.dist-info/entry_points.txt
code_savior-1.0.dist-info/top_level.txt
code_savior-1.0.dist-info/RECORD
