Metadata-Version: 2.1
Name: code-savior
Version: 1.0
Summary: good to generate a brief commit
Home-page: https://github.com/Orwlit/code-savior
Author: Yuzhe Wang (GitHub: Orwlit)
Author-email: orwlit31@outlook.com
Classifier: Programming Language :: Python :: 3
Classifier: License :: OSI Approved :: MIT License
Classifier: Operating System :: OS Independent
Requires-Python: >=3.10
License-File: LICENSE
Requires-Dist: inquirer
Requires-Dist: rich
Requires-Dist: argparse
Requires-Dist: openai
Requires-Dist: python-dotenv
